{
  "job_title": "Dynamics 365 CE Developer",
  "job_purpose": "Designing and implementing solutions using the Dynamics 365 Customer Engagement platform with a focus on customization, integration, and technical support.",
  "keywords": [
    "Dynamics 365 CE development",
    "Microsoft Power Platform",
    "C#",
    ".NET",
    "JavaScript",
    "Azure services",
    "Agile",
    "Scrum methodologies",
    "SQL",
    "RESTful APIs",
    "Git",
    "Project management",
    "Time management",
    "Microsoft Certified: Dynamics 365 Customer Service Functional Consultant Associate certification",
    "Exam PL-200: Microsoft Power Platform Functional Consultant",
    "Microsoft Applied Skills: Create and manage automated processes by using Power Automate",
    "Microsoft Applied Skills: Create and manage model-driven apps with Power Apps and Dataverse"
  ],
  "job_duties_and_responsibilities": [
    "Design and implement solutions using Dynamics 365 CE platform.",
    "Customize applications to meet business requirements.",
    "Integrate Dynamics 365 CE with external systems.",
    "Conduct system testing and debugging.",
    "Provide technical support and troubleshooting.",
    "Collaborate with stakeholders for requirement analysis.",
    "Develop and maintain technical documentation.",
    "Train end-users on functionalities and best practices.",
    "Participate in deployment and configuration.",
    "Stay updated with latest features and updates."
  ],
  "required_qualifications": [
    "Proficiency in Dynamics 365 CE development.",
    "Strong understanding of Microsoft Power Platform.",
    "Experience with C#, .NET, and JavaScript.",
    "Knowledge of data integration tools and techniques.",
    "Familiarity with Azure services and environments.",
    "Ability to customize and configure Dynamics 365 CE solutions.",
    "Problem-solving skills for technical challenges.",
    "Experience with Agile or Scrum methodologies.",
    "Strong communication skills.",
    "Attention to detail in coding and documentation."
  ],
  "preferred_qualifications": [
    "Understanding of relational databases and SQL.",
    "Experience with RESTful APIs and web services.",
    "Knowledge of version control systems like Git.",
    "Skills in project management and time management.",
    "Ability to adapt to new technologies and tools.",
    "Microsoft Certified: Dynamics 365 Customer Service Functional Consultant Associate certification.",
    "Any of the following certifications:",
    "Exam PL-200: Microsoft Power Platform Functional Consultant.",
    "Microsoft Applied Skills: Create and manage automated processes by using Power Automate.",
    "Microsoft Applied Skills: Create and manage model-driven apps with Power Apps and Dataverse."
  ],
  "company_name": "Akkodis",
  "company_details": "Akkodis is a commercial brand under which both AKKA and Modis entities operate. Akkodis is an Equal Opportunity employer, committed to all forms of workforce inclusion. We actively invite and encourage applications by candidates from diverse backgrounds."
}